<?xml version="1.0" encoding="utf-8"?>
<!-- $Id$ -->
<MultiClient>
  <StationInfo>
    Station  = NTZ
    Computer = Latitude E6430 : N-Series Base
  </StationInfo>
  <server host="cpcfcmd.evn.np.kn.nz.dlr.de"
	  port="40028">
  </server>
  <FileSink filePath="DataMUN"
            filePeriod="1d">
  </FileSink>
  <Streams>
<!-- uncomment for recording EFR telegramms
    <Stream pattern="E.*">Writer</Stream>
-->
    <Stream pattern="L.*">Writer</Stream>
    <Stream pattern="M.*">Writer</Stream>
  </Streams>
  <Clients>
    <Writer type="WriterTXT"
            filePath="DataMUN"
            filePeriod="1d">
    </Writer>
  </Clients>
</MultiClient>
